{
  "gitSyncId": "66d7da81444411108d7b0c10_18625765-2cfa-4bfc-8511-3fa053a65d90",
  "id": "Verify_ApiKeyCloakGetToken",
  "pluginId": "restapi-plugin",
  "pluginType": "API",
  "unpublishedAction": {
    "actionConfiguration": {
      "autoGeneratedHeaders": [
        {
          "key": "content-type",
          "value": "application/x-www-form-urlencoded"
        }
      ],
      "body": "",
      "bodyFormData": [
        {
          "key": "client_id",
          "value": "asd-cando"
        },
        {
          "key": "grant_type",
          "value": "authorization_code"
        },
        {
          "key": "code",
          "value": "{{this.params.code}}"
        },
        {
          "key": "redirect_uri",
          "value": "https://appsmith.clicksbiz.com/app/purchase-request/verify-66d80ef5444411108d7b0c4c"
        }
      ],
      "encodeParamsToggle": true,
      "formData": {
        "apiContentType": "application/x-www-form-urlencoded"
      },
      "headers": [],
      "httpMethod": "POST",
      "httpVersion": "HTTP11",
      "paginationType": "NONE",
      "path": "/realms/SCGJWD-Portal/protocol/openid-connect/token",
      "pluginSpecifiedTemplates": [
        {
          "value": true
        }
      ],
      "queryParameters": [],
      "timeoutInMillisecond": 10000
    },
    "confirmBeforeExecute": false,
    "datasource": {
      "isAutoGenerated": false,
      "name": "DEFAULT_REST_DATASOURCE",
      "pluginId": "restapi-plugin"
    },
    "dynamicBindingPathList": [
      {
        "key": "bodyFormData[2].value"
      }
    ],
    "executeOnLoad": false,
    "name": "ApiKeyCloakGetToken",
    "pageId": "Verify",
    "userSetOnLoad": false
  }
}